pg_mysql/__init__.py
pg_mysql/define.py
pg_mysql/mysql.py
pg_mysql/sa_mysql.py
pg_mysql-1.0.3.dist-info/METADATA
pg_mysql-1.0.3.dist-info/WHEEL
pg_mysql-1.0.3.dist-info/top_level.txt
pg_mysql-1.0.3.dist-info/RECORD
