Metadata-Version: 2.1
Name: pg_mysql
Version: 1.0.3
Summary: python game: mysql
Author: baozilaji@gmail.com
Requires-Python: >=3.9
Requires-Dist: pg-environment >=0
Requires-Dist: SQLAlchemy ==1.4.27
Requires-Dist: python-dateutil ==2.8.2
Requires-Dist: aiomysql ==0.1.1
